aws_ec2/__init__.py
aws_ec2/instances.py
aws_ec2/credentials/__init__.py
aws_ec2-1.0.1.dev20180715112653.dist-info/METADATA
aws_ec2-1.0.1.dev20180715112653.dist-info/RECORD
aws_ec2-1.0.1.dev20180715112653.dist-info/WHEEL
aws_ec2-1.0.1.dev20180715112653.dist-info/top_level.txt
