Metadata-Version: 2.1
Name: aws-ec2
Version: 1.0.1.dev20180715112653
Summary: AWS EC2 Python Library
Home-page: https://gitlab.com/robot-keywords/aws-ec2
Author: An Nguyen
Author-email: nthienan.it@gmail.com
License: MIT
Project-URL: Bug Reports, https://gitlab.com/robot-keywords/aws-ec2/issues
Project-URL: Source, https://gitlab.com/robot-keywords/aws-ec2
Keywords: aws-ec2
Platform: UNKNOWN
Classifier: Development Status :: 3 - Alpha
Classifier: Intended Audience :: Developers
Classifier: Topic :: Software Development :: Testing
Classifier: License :: OSI Approved :: MIT License
Classifier: Programming Language :: Python :: 2.7
Classifier: Programming Language :: Python :: 3.6
Requires-Dist: boto3 (==1.7.4)
